{
  "sections": [
    {
      "section_name": "BREADCRUMB",
      "widgets": [
        {
          "widget_type": "BREADCRUMB",
          "data": {
            "@type": "type.googleapis.com/widgets.BreadcrumbData",
            "parent_items": [
              {
                "title": "وسایل نقلیه",
                "action": {
                  "type": "OPEN_POSTLIST_PAGE_GRPC",
                  "payload": {
                    "@type": "type.googleapis.com/widgets.OpenPostListPageGRPCPayload",
                    "search_data": {
                      "form_data": {
                        "data": {
                          "category": {
                            "str": {
                              "value": "vehicles"
                            }
                          }
                        }
                      }
                    },
                    "source_view": "CATEGORY_BREAD_CRUMB",
                    "source_view_str": "CATEGORY_BREAD_CRUMB"
                  }
                }
              },
              {
                "title": "قطعات یدکی و لوازم جانبی",
                "action": {
                  "type": "OPEN_POSTLIST_PAGE_GRPC",
                  "payload": {
                    "@type": "type.googleapis.com/widgets.OpenPostListPageGRPCPayload",
                    "search_data": {
                      "form_data": {
                        "data": {
                          "category": {
                            "str": {
                              "value": "parts-accessories"
                            }
                          }
                        }
                      }
                    },
                    "source_view": "CATEGORY_BREAD_CRUMB",
                    "source_view_str": "CATEGORY_BREAD_CRUMB"
                  }
                }
              }
            ],
            "current_page_title": "دزدگیر ایزی کار اصلی کره ای",
            "padded": true
          }
        }
      ]
    },
    {
      "section_name": "TITLE",
      "widgets": [
        {
          "widget_type": "LEGEND_TITLE_ROW",
          "data": {
            "@type": "type.googleapis.com/widgets.LegendTitleRowData",
            "title": "دزدگیر ایزی کار اصلی کره ای",
            "subtitle": "۳ روز پیش در مشهد، شهید معقول",
            "high_level_heading": true
          }
        },
        {
          "widget_type": "SELECTOR_ROW",
          "data": {
            "@type": "type.googleapis.com/widgets.SelectorRowData",
            "title": "زنگ خطرهای قبل از معامله",
            "action": {
              "type": "OPEN_PAGE",
              "payload": {
                "@type": "type.googleapis.com/widgets.OpenPagePayload",
                "request_http_method": "POST",
                "request_data": {
                  "@type": "type.googleapis.com/post_api_v2.GetFraudAlertPageRequest.Data",
                  "category": "parts-accessories"
                },
                "specification": {
                  "@type": "type.googleapis.com/widgets.OpenPagePayload.SimplePageSpecification",
                  "navigation_button": "BACK"
                },
                "is_modal": true,
                "rest_request_path": "/v8/postview/fraud-alert",
                "grpc_request_path": "/post_api_v2.PostApi/GetFraudAlertPage"
              }
            },
            "has_divider": true,
            "icon": {
              "image_url_dark": "https://s100.divarcdn.com/static/imgs/widget-icons/dark/icon_secondary/v1/warning.png",
              "image_url_light": "https://s100.divarcdn.com/static/imgs/widget-icons/light/icon_secondary/v1/warning.png",
              "icon_name": "WARNING",
              "icon_color": "ICON_SECONDARY"
            },
            "has_arrow": true,
            "last_notification_date": "0001-01-01T00:00:00Z"
          },
          "action_log": {
            "server_side_info": {
              "info": {
                "@type": "type.googleapis.com/action_log.PostWarningInfo",
                "post_token": "Aas7RYZl"
              },
              "item_type": {
                "type": "POST_WARNING"
              }
            },
            "enabled": true
          }
        }
      ]
    },
    {
      "section_name": "DESCRIPTION",
      "widgets": [
        {
          "widget_type": "TITLE_ROW",
          "data": {
            "@type": "type.googleapis.com/widgets.TitleRowData",
            "text": "توضیحات",
            "text_color": "TEXT_PRIMARY",
            "text_type": "SECONDARY"
          }
        },
        {
          "widget_type": "DESCRIPTION_ROW",
          "data": {
            "@type": "type.googleapis.com/widgets.DescriptionRowData",
            "text": "باسلام دزدگیر اصلی ایزی کار اصل کره ای\nدزدگیرسالم همه چیزش اوکی قابل نصب و استفاده قیمت خوب اصل کره درب خانه خریداری نمائید خاطرجمع\nلطفا تماس بگیرید درطول روز\nممنون از دیوار",
            "is_primary": true
          }
        }
      ]
    },
    {
      "section_name": "IMAGE",
      "widgets": [
        {
          "widget_type": "IMAGE_CAROUSEL",
          "data": {
            "@type": "type.googleapis.com/widgets.ImageCarouselData",
            "items": [
              {
                "image": {
                  "url": "https://s100.divarcdn.com/static/photo/neda/webp_post/4TsJnIq6iVKDU_0vWchLXw/07fce0c9-32e5-46e0-9994-39aeaffb88fb.webp",
                  "alt": "دزدگیر ایزی کار اصلی کره ای|قطعات یدکی و لوازم جانبی|مشهد, شهید معقول|دیوار",
                  "thumbnail_url": "https://s100.divarcdn.com/static/photo/neda/webp_thumbnail/fkS01hM-YrsLjAWWB5MWEA/07fce0c9-32e5-46e0-9994-39aeaffb88fb.webp"
                }
              },
              {
                "image": {
                  "url": "https://s100.divarcdn.com/static/photo/neda/webp_post/fjEVTeUbpzAeRM50lo4pkA/980b4e44-5ec5-4ade-beb2-1828a65bb2f2.webp",
                  "alt": "دزدگیر ایزی کار اصلی کره ای|قطعات یدکی و لوازم جانبی|مشهد, شهید معقول|دیوار",
                  "thumbnail_url": "https://s100.divarcdn.com/static/photo/neda/webp_thumbnail/ggY9mL-H_5YWHeKG70PdYg/980b4e44-5ec5-4ade-beb2-1828a65bb2f2.webp"
                }
              },
              {
                "image": {
                  "url": "https://s100.divarcdn.com/static/photo/neda/webp_post/SyXt4awu8_dB-5USmyjj4Q/2dabc5a0-5d26-40b7-82f2-8d9d59ff4bc2.webp",
                  "alt": "دزدگیر ایزی کار اصلی کره ای|قطعات یدکی و لوازم جانبی|مشهد, شهید معقول|دیوار",
                  "thumbnail_url": "https://s100.divarcdn.com/static/photo/neda/webp_thumbnail/ujOkySshPYZnLqHypnJ3ZA/2dabc5a0-5d26-40b7-82f2-8d9d59ff4bc2.webp"
                }
              },
              {
                "image": {
                  "url": "https://s100.divarcdn.com/static/photo/neda/webp_post/wFXaC3lwNXKSex7GnOtK8Q/3209f9c0-354c-4e6a-b83a-98efdd7111c0.webp",
                  "alt": "دزدگیر ایزی کار اصلی کره ای|قطعات یدکی و لوازم جانبی|مشهد, شهید معقول|دیوار",
                  "thumbnail_url": "https://s100.divarcdn.com/static/photo/neda/webp_thumbnail/HZJY9ywLiR8nIbZ640pPng/3209f9c0-354c-4e6a-b83a-98efdd7111c0.webp"
                }
              },
              {
                "image": {
                  "url": "https://s100.divarcdn.com/static/photo/neda/webp_post/dmW3U18Cb6gK5-CN0x0e5g/c60357fd-936f-4193-bf53-066527bcc99e.webp",
                  "alt": "دزدگیر ایزی کار اصلی کره ای|قطعات یدکی و لوازم جانبی|مشهد, شهید معقول|دیوار",
                  "thumbnail_url": "https://s100.divarcdn.com/static/photo/neda/webp_thumbnail/YtvwQ8tfkgNIzg2BC3D-Bw/c60357fd-936f-4193-bf53-066527bcc99e.webp"
                }
              },
              {
                "image": {
                  "url": "https://s100.divarcdn.com/static/photo/neda/webp_post/GnV9tH-I6Q730N9L0Yc4rg/6cc9d1ff-0929-4aca-9faa-c1a6845230ab.webp",
                  "alt": "دزدگیر ایزی کار اصلی کره ای|قطعات یدکی و لوازم جانبی|مشهد, شهید معقول|دیوار",
                  "thumbnail_url": "https://s100.divarcdn.com/static/photo/neda/webp_thumbnail/WDJZe6iFxck63rODuen81A/6cc9d1ff-0929-4aca-9faa-c1a6845230ab.webp"
                }
              }
            ],
            "image_aspect_ratio": {
              "dynamic_aspect_ratio": {
                "height": 3,
                "width": 4
              }
            },
            "has_preview": true,
            "has_thumbnails": true
          }
        }
      ]
    },
    {
      "section_name": "LIST_DATA",
      "widgets": [
        {
          "widget_type": "UNEXPANDABLE_ROW",
          "data": {
            "@type": "type.googleapis.com/widgets.UnexpandableRowData",
            "title": "قیمت",
            "value": "‏۲،۰۰۰،۰۰۰ تومان",
            "has_divider": true
          }
        },
        {
          "widget_type": "LAZY_SECTION",
          "data": {
            "@type": "type.googleapis.com/widgets.LazySectionData",
            "rest_request_path": "/v1/open-platform/addons/lazy",
            "grpc_request_path": "/addons.Addons/GetLazyAddons",
            "request_data": {
              "@type": "type.googleapis.com/addons.GetLazyAddonsRequest.RequestData",
              "token": "Aas7RYZl",
              "source": "POST_APPROVED",
              "category": "parts-accessories",
              "city_id": 3,
              "include_post_addons": true
            }
          }
        }
      ]
    },
    {
      "section_name": "TAGS",
      "widgets": [
        {
          "widget_type": "WRAPPER_ROW",
          "data": {
            "@type": "type.googleapis.com/widgets.WrapperRowData",
            "chip_list": {
              "chips": [
                {
                  "text": "قطعات یدکی و لوازم جانبی",
                  "type": "ACTION",
                  "action": {
                    "type": "OPEN_POSTLIST_PAGE_GRPC",
                    "payload": {
                      "@type": "type.googleapis.com/widgets.OpenPostListPageGRPCPayload",
                      "search_data": {
                        "form_data": {
                          "data": {
                            "category": {
                              "str": {
                                "value": "parts-accessories"
                              }
                            }
                          }
                        }
                      },
                      "source_view": "CATEGORY_BREAD_CRUMB",
                      "source_view_str": "CATEGORY_BREAD_CRUMB"
                    }
                  }
                },
                {
                  "text": "قطعات یدکی و لوازم جانبی در شهید معقول",
                  "type": "ACTION",
                  "action": {
                    "type": "OPEN_POSTLIST_PAGE_GRPC",
                    "payload": {
                      "@type": "type.googleapis.com/widgets.OpenPostListPageGRPCPayload",
                      "search_data": {
                        "form_data": {
                          "data": {
                            "category": {
                              "str": {
                                "value": "parts-accessories"
                              }
                            },
                            "districts": {
                              "repeated_string": {
                                "value": [
                                  "1216"
                                ]
                              }
                            }
                          }
                        }
                      },
                      "source_view": "CATEGORY_BREAD_CRUMB",
                      "source_view_str": "CATEGORY_BREAD_CRUMB"
                    }
                  }
                }
              ]
            }
          }
        }
      ]
    },
    {
      "section_name": "NOTE",
      "widgets": [
        {
          "widget_type": "NOTE",
          "data": {
            "@type": "type.googleapis.com/widgets.NoteData",
            "title": "یادداشت من",
            "button_title": "ویرایش یادداشت",
            "post_token": "Aas7RYZl"
          }
        }
      ]
    },
    {
      "section_name": "STATIC",
      "widgets": [
        {
          "widget_type": "SECTION_DIVIDER_ROW",
          "data": {
            "@type": "type.googleapis.com/widgets.SectionDividerRowData",
            "padded": true
          }
        },
        {
          "widget_type": "SELECTOR_ROW",
          "data": {
            "@type": "type.googleapis.com/widgets.SelectorRowData",
            "title": "گزارش آگهی",
            "action": {
              "type": "OPEN_SCHEMA_PAGE",
              "payload": {
                "@type": "type.googleapis.com/widgets.OpenSchemaPagePayload",
                "additional_data": {
                  "@type": "type.googleapis.com/widgets.GetFeedbackPageRequest.AdditionalData",
                  "post_token": "Aas7RYZl"
                },
                "is_modal": true,
                "rest_request_path": "/v8/post-quality/feedback-v2",
                "grpc_request_path": "/post_quality.PostQualityFeedback/GetFeedbackPage"
              }
            },
            "has_divider": true,
            "icon": {
              "image_url_dark": "https://s100.divarcdn.com/static/imgs/widget-icons/dark/icon_secondary/v1/report.png",
              "image_url_light": "https://s100.divarcdn.com/static/imgs/widget-icons/light/icon_secondary/v1/report.png",
              "icon_name": "REPORT",
              "icon_color": "ICON_SECONDARY"
            },
            "has_arrow": true,
            "last_notification_date": "0001-01-01T00:00:00Z"
          }
        }
      ]
    }
  ],
  "share": {
    "title": "دزدگیر ایزی کار اصلی کره ای",
    "web_url": "https://divar.ir/v/Aas7RYZl"
  },
  "seo": {
    "title": "دزدگیر ایزی کار اصلی کره ای در مشهد",
    "description": "آگهی دزدگیر ایزی کار اصلی کره ای در دیوار مشهد",
    "android_package_name": "ir.divar",
    "android_app_url": "android-app://ir.divar/http/v/دزدگیر ایزی کار اصلی کره ای/Aas7RYZl/",
    "web_info": {
      "title": "دزدگیر ایزی کار اصلی کره ای",
      "district_persian": "شهید معقول",
      "city_persian": "مشهد",
      "category_slug_persian": "قطعات یدکی و لوازم جانبی"
    },
    "unavailable_after": "2025-11-13T01:02:34.1488",
    "bread_crumb": [
      {
        "name": "قطعات یدکی و لوازم جانبی",
        "search_data": {
          "form_data": {
            "data": {
              "districts": {
                "repeated_string": {
                  "value": [
                    "1216"
                  ]
                }
              },
              "category": {
                "str": {
                  "value": "parts-accessories"
                }
              }
            }
          }
        }
      },
      {
        "name": "وسایل نقلیه",
        "search_data": {
          "form_data": {
            "data": {
              "category": {
                "str": {
                  "value": "vehicles"
                }
              },
              "districts": {
                "repeated_string": {
                  "value": [
                    "1216"
                  ]
                }
              }
            }
          }
        }
      },
      {
        "name": "شهید معقول",
        "search_data": {
          "form_data": {
            "data": {
              "districts": {
                "repeated_string": {
                  "value": [
                    "1216"
                  ]
                }
              }
            }
          }
        }
      },
      {
        "name": "3",
        "search_data": {
          "form_data": {}
        }
      },
      {
        "name": "دیوار"
      }
    ],
    "post_seo_schema": {
      "category": "parts-accessories",
      "@context": "https://schema.org",
      "@type": "Product",
      "url": "https://divar.ir/v/دزدگیر-ایزی-کار-اصلی-کره-ای/Aas7RYZl",
      "image": "https://s100.divarcdn.com/static/photo/neda/webp_post/4TsJnIq6iVKDU_0vWchLXw/07fce0c9-32e5-46e0-9994-39aeaffb88fb.webp",
      "web_info": {
        "city_persian": "مشهد",
        "district_persian": "شهید معقول",
        "category_slug_persian": "قطعات یدکی و لوازم جانبی",
        "title": "دزدگیر ایزی کار اصلی کره ای"
      },
      "description": "باسلام دزدگیر اصلی ایزی کار اصل کره ای\nدزدگیرسالم همه چیزش اوکی قابل نصب و استفاده قیمت خوب اصل کره درب خانه خریداری نمائید خاطرجمع\nلطفا تماس بگیرید درطول روز\nممنون از دیوار",
      "offers": {
        "@type": "Offer",
        "priceCurrency": "IRR",
        "price": "2000000"
      },
      "name": "دزدگیر ایزی کار اصلی کره ای"
    }
  },
  "contact": {
    "chat_enabled": true,
    "action_log": {
      "server_side_info": {
        "info": {
          "@type": "type.googleapis.com/action_log.ContactInfoInfo",
          "post_token": "Aas7RYZl",
          "method_name": "GetContactWeb",
          "contact_uuid": "7d695a9f-173d-428d-be5b-c58bdb81eab5"
        },
        "item_type": {
          "type": "CONTACT_INFO"
        }
      },
      "enabled": true
    },
    "contact_uuid": "7d695a9f-173d-428d-be5b-c58bdb81eab5"
  },
  "webengage": {
    "cat_3": "",
    "district": "shahid-maqoul",
    "business_type": "personal",
    "cat_2": "parts-accessories",
    "city": "mashhad",
    "token": "Aas7RYZl",
    "category": "parts-accessories",
    "image_count": 6,
    "source_view": "",
    "credit": 0,
    "gender": "",
    "rent": 0,
    "status": "",
    "brand_model": "",
    "price": 2000000,
    "cat_1": "vehicles",
    "business_ref": "",
    "originality": ""
  },
  "analytics": {
    "cat1": "vehicles",
    "cat2": "parts-accessories",
    "city": "mashhad"
  },
  "city": {
    "city_id": "3",
    "name": "مشهد",
    "parent_id": "880",
    "second_slug": "mashhad"
  }
}