{
  "sections": [
    {
      "section_name": "BREADCRUMB",
      "widgets": [
        {
          "widget_type": "BREADCRUMB",
          "data": {
            "@type": "type.googleapis.com/widgets.BreadcrumbData",
            "parent_items": [
              {
                "title": "وسایل نقلیه",
                "action": {
                  "type": "OPEN_POSTLIST_PAGE_GRPC",
                  "payload": {
                    "@type": "type.googleapis.com/widgets.OpenPostListPageGRPCPayload",
                    "search_data": {
                      "form_data": {
                        "data": {
                          "category": {
                            "str": {
                              "value": "vehicles"
                            }
                          }
                        }
                      }
                    },
                    "source_view": "CATEGORY_BREAD_CRUMB",
                    "source_view_str": "CATEGORY_BREAD_CRUMB"
                  }
                }
              },
              {
                "title": "قطعات یدکی و لوازم جانبی",
                "action": {
                  "type": "OPEN_POSTLIST_PAGE_GRPC",
                  "payload": {
                    "@type": "type.googleapis.com/widgets.OpenPostListPageGRPCPayload",
                    "search_data": {
                      "form_data": {
                        "data": {
                          "category": {
                            "str": {
                              "value": "parts-accessories"
                            }
                          }
                        }
                      }
                    },
                    "source_view": "CATEGORY_BREAD_CRUMB",
                    "source_view_str": "CATEGORY_BREAD_CRUMB"
                  }
                }
              }
            ],
            "current_page_title": "ساخت و تعمیر سویچ و ریموت انواع خودرو",
            "padded": true
          }
        }
      ]
    },
    {
      "section_name": "TITLE",
      "widgets": [
        {
          "widget_type": "LEGEND_TITLE_ROW",
          "data": {
            "@type": "type.googleapis.com/widgets.LegendTitleRowData",
            "title": "ساخت و تعمیر سویچ و ریموت انواع خودرو",
            "subtitle": "۱ هفته پیش در مشهد، آزادشهر",
            "high_level_heading": true
          }
        },
        {
          "widget_type": "SELECTOR_ROW",
          "data": {
            "@type": "type.googleapis.com/widgets.SelectorRowData",
            "title": "زنگ خطرهای قبل از معامله",
            "action": {
              "type": "OPEN_PAGE",
              "payload": {
                "@type": "type.googleapis.com/widgets.OpenPagePayload",
                "request_http_method": "POST",
                "request_data": {
                  "@type": "type.googleapis.com/post_api_v2.GetFraudAlertPageRequest.Data",
                  "category": "parts-accessories"
                },
                "specification": {
                  "@type": "type.googleapis.com/widgets.OpenPagePayload.SimplePageSpecification",
                  "navigation_button": "BACK"
                },
                "is_modal": true,
                "rest_request_path": "/v8/postview/fraud-alert",
                "grpc_request_path": "/post_api_v2.PostApi/GetFraudAlertPage"
              }
            },
            "has_divider": true,
            "icon": {
              "image_url_dark": "https://s100.divarcdn.com/static/imgs/widget-icons/dark/icon_secondary/v1/warning.png",
              "image_url_light": "https://s100.divarcdn.com/static/imgs/widget-icons/light/icon_secondary/v1/warning.png",
              "icon_name": "WARNING",
              "icon_color": "ICON_SECONDARY"
            },
            "has_arrow": true,
            "last_notification_date": "0001-01-01T00:00:00Z"
          },
          "action_log": {
            "server_side_info": {
              "info": {
                "@type": "type.googleapis.com/action_log.PostWarningInfo",
                "post_token": "Aa9yxyiS"
              },
              "item_type": {
                "type": "POST_WARNING"
              }
            },
            "enabled": true
          }
        }
      ]
    },
    {
      "section_name": "DESCRIPTION",
      "widgets": [
        {
          "widget_type": "TITLE_ROW",
          "data": {
            "@type": "type.googleapis.com/widgets.TitleRowData",
            "text": "توضیحات",
            "text_color": "TEXT_PRIMARY",
            "text_type": "SECONDARY"
          }
        },
        {
          "widget_type": "DESCRIPTION_ROW",
          "data": {
            "@type": "type.googleapis.com/widgets.DescriptionRowData",
            "text": "• ساخت سویچ و ریموت گمشده انواع خودروهای ایرانی و خارجی  \n• تعمیر و کددهی ریموت دزدگیر  \n• نصب انواع جی پی اس   \n• خدمات سریع و تخصصی در محل  \n• فروشگاه معتبر در نبش جلال آل احمد ۵۹  \nبرای مشاوره و قیمت، تماس بگیرید!",
            "is_primary": true
          }
        }
      ]
    },
    {
      "section_name": "IMAGE",
      "widgets": [
        {
          "widget_type": "IMAGE_CAROUSEL",
          "data": {
            "@type": "type.googleapis.com/widgets.ImageCarouselData",
            "items": [
              {
                "image": {
                  "url": "https://s100.divarcdn.com/static/photo/neda/post/_NsFyCivVhl-G2jKoaqVew/f80780a4-cb6f-4a5f-9228-20d9a7b71e89.jpg.jpg",
                  "alt": "ساخت و تعمیر سویچ و ریموت انواع خودرو|قطعات یدکی و لوازم جانبی|مشهد, آزادشهر|دیوار",
                  "thumbnail_url": "https://s100.divarcdn.com/static/photo/neda/webp_thumbnail/HFYXtStwGKQnsa6F8Zpehg/f80780a4-cb6f-4a5f-9228-20d9a7b71e89.jpg.webp"
                }
              },
              {
                "image": {
                  "url": "https://s100.divarcdn.com/static/photo/neda/post/H2OmHtexOuhM9cqeeM0X1Q/5928669c-c52a-4555-b3ab-7f1541315376.jpg.jpg",
                  "alt": "ساخت و تعمیر سویچ و ریموت انواع خودرو|قطعات یدکی و لوازم جانبی|مشهد, آزادشهر|دیوار",
                  "thumbnail_url": "https://s100.divarcdn.com/static/photo/neda/webp_thumbnail/yxkqFISKYKWgrQiiiB5nhw/5928669c-c52a-4555-b3ab-7f1541315376.jpg.webp"
                }
              },
              {
                "image": {
                  "url": "https://s100.divarcdn.com/static/photo/neda/post/YehZ0siWVn3GD12ox_ow9g/b75dbbd2-62d7-4766-a9f2-7d4c00f1c585.jpg.jpg",
                  "alt": "ساخت و تعمیر سویچ و ریموت انواع خودرو|قطعات یدکی و لوازم جانبی|مشهد, آزادشهر|دیوار",
                  "thumbnail_url": "https://s100.divarcdn.com/static/photo/neda/webp_thumbnail/7aP3sn8B6aXke5OW8evnAw/b75dbbd2-62d7-4766-a9f2-7d4c00f1c585.jpg.webp"
                }
              },
              {
                "image": {
                  "url": "https://s100.divarcdn.com/static/photo/neda/post/Pu3rRB65lTvtS48cheOCuA/f13996f5-01f0-4715-88b5-bb3db5532ccf.jpg.jpg",
                  "alt": "ساخت و تعمیر سویچ و ریموت انواع خودرو|قطعات یدکی و لوازم جانبی|مشهد, آزادشهر|دیوار",
                  "thumbnail_url": "https://s100.divarcdn.com/static/photo/neda/webp_thumbnail/KOK-UwC8gbZ4bXlibOHuaQ/f13996f5-01f0-4715-88b5-bb3db5532ccf.jpg.webp"
                }
              },
              {
                "image": {
                  "url": "https://s100.divarcdn.com/static/photo/neda/post/r-samgezfzwZit75oV7zxw/690d139f-bf75-4a81-8dee-7178444026df.jpg.jpg",
                  "alt": "ساخت و تعمیر سویچ و ریموت انواع خودرو|قطعات یدکی و لوازم جانبی|مشهد, آزادشهر|دیوار",
                  "thumbnail_url": "https://s100.divarcdn.com/static/photo/neda/webp_thumbnail/gBxYMfvb8kMYyF-uQdlbcA/690d139f-bf75-4a81-8dee-7178444026df.jpg.webp"
                }
              },
              {
                "image": {
                  "url": "https://s100.divarcdn.com/static/photo/neda/post/Re4QRFJv6C9dn3kOOJzgPQ/81a072aa-d319-4440-b25c-c5ce148f92c0.jpg.jpg",
                  "alt": "ساخت و تعمیر سویچ و ریموت انواع خودرو|قطعات یدکی و لوازم جانبی|مشهد, آزادشهر|دیوار",
                  "thumbnail_url": "https://s100.divarcdn.com/static/photo/neda/webp_thumbnail/qk8oIKaCQ6b8U1dZU_Wqlg/81a072aa-d319-4440-b25c-c5ce148f92c0.jpg.webp"
                }
              },
              {
                "image": {
                  "url": "https://s100.divarcdn.com/static/photo/neda/post/XFfzoHve_IVfb2onulZjFQ/dbd0b1e5-e253-46a5-9629-04a52e0ba662.jpg.jpg",
                  "alt": "ساخت و تعمیر سویچ و ریموت انواع خودرو|قطعات یدکی و لوازم جانبی|مشهد, آزادشهر|دیوار",
                  "thumbnail_url": "https://s100.divarcdn.com/static/photo/neda/webp_thumbnail/TRdHvkWHPTbmGheXH4R2Vg/dbd0b1e5-e253-46a5-9629-04a52e0ba662.jpg.webp"
                }
              }
            ],
            "image_aspect_ratio": {
              "dynamic_aspect_ratio": {
                "height": 3,
                "width": 4
              }
            },
            "has_preview": true,
            "has_thumbnails": true
          }
        }
      ]
    },
    {
      "section_name": "LIST_DATA",
      "widgets": [
        {
          "widget_type": "UNEXPANDABLE_ROW",
          "data": {
            "@type": "type.googleapis.com/widgets.UnexpandableRowData",
            "title": "قیمت",
            "value": "‏۱۲،۰۰۰ تومان",
            "has_divider": true
          }
        },
        {
          "widget_type": "LAZY_SECTION",
          "data": {
            "@type": "type.googleapis.com/widgets.LazySectionData",
            "rest_request_path": "/v1/open-platform/addons/lazy",
            "grpc_request_path": "/addons.Addons/GetLazyAddons",
            "request_data": {
              "@type": "type.googleapis.com/addons.GetLazyAddonsRequest.RequestData",
              "token": "Aa9yxyiS",
              "source": "POST_APPROVED",
              "category": "parts-accessories",
              "city_id": 3
            }
          }
        }
      ]
    },
    {
      "section_name": "TAGS",
      "widgets": [
        {
          "widget_type": "WRAPPER_ROW",
          "data": {
            "@type": "type.googleapis.com/widgets.WrapperRowData",
            "chip_list": {
              "chips": [
                {
                  "text": "قطعات یدکی و لوازم جانبی",
                  "type": "ACTION",
                  "action": {
                    "type": "OPEN_POSTLIST_PAGE_GRPC",
                    "payload": {
                      "@type": "type.googleapis.com/widgets.OpenPostListPageGRPCPayload",
                      "search_data": {
                        "form_data": {
                          "data": {
                            "category": {
                              "str": {
                                "value": "parts-accessories"
                              }
                            }
                          }
                        }
                      },
                      "source_view": "CATEGORY_BREAD_CRUMB",
                      "source_view_str": "CATEGORY_BREAD_CRUMB"
                    }
                  }
                },
                {
                  "text": "قطعات یدکی و لوازم جانبی در آزادشهر",
                  "type": "ACTION",
                  "action": {
                    "type": "OPEN_POSTLIST_PAGE_GRPC",
                    "payload": {
                      "@type": "type.googleapis.com/widgets.OpenPostListPageGRPCPayload",
                      "search_data": {
                        "form_data": {
                          "data": {
                            "category": {
                              "str": {
                                "value": "parts-accessories"
                              }
                            },
                            "districts": {
                              "repeated_string": {
                                "value": [
                                  "431"
                                ]
                              }
                            }
                          }
                        }
                      },
                      "source_view": "CATEGORY_BREAD_CRUMB",
                      "source_view_str": "CATEGORY_BREAD_CRUMB"
                    }
                  }
                },
                {
                  "text": "دزدگیر خودرو",
                  "type": "ACTION",
                  "action": {
                    "type": "OPEN_WEB_PAGE",
                    "payload": {
                      "@type": "type.googleapis.com/widgets.OpenWebPagePayload",
                      "link": "https://divar.ir/s/mashhad/list/دزدگیر-خودرو",
                      "page_type": "SAME_PAGE"
                    }
                  }
                }
              ]
            }
          }
        }
      ]
    },
    {
      "section_name": "MAP",
      "widgets": [
        {
          "widget_type": "MAP_ROW",
          "data": {
            "@type": "type.googleapis.com/widgets.MapRowData",
            "location": {
              "exact_data": {
                "point": {
                  "latitude": 36.331425,
                  "longitude": 59.537254
                }
              }
            },
            "image_url": "https://api.divar.ir/v8/mapimage?encrypted_data=MTIzNDU2Nzg5MTIzXJRmerMyPa_uQq1lG5zqH_5Lp6HvIX0lr1A4N5z1cp6THw=="
          },
          "action_log": {
            "server_side_info": {
              "info": {
                "@type": "type.googleapis.com/action_log.MapInfo",
                "post_token": "Aa9yxyiS"
              },
              "item_type": {
                "type": "MAP"
              }
            },
            "enabled": true
          }
        }
      ]
    },
    {
      "section_name": "NOTE",
      "widgets": [
        {
          "widget_type": "NOTE",
          "data": {
            "@type": "type.googleapis.com/widgets.NoteData",
            "title": "یادداشت من",
            "button_title": "ویرایش یادداشت",
            "post_token": "Aa9yxyiS"
          }
        }
      ]
    },
    {
      "section_name": "STATIC",
      "widgets": [
        {
          "widget_type": "SECTION_DIVIDER_ROW",
          "data": {
            "@type": "type.googleapis.com/widgets.SectionDividerRowData",
            "padded": true
          }
        },
        {
          "widget_type": "SELECTOR_ROW",
          "data": {
            "@type": "type.googleapis.com/widgets.SelectorRowData",
            "title": "گزارش آگهی",
            "action": {
              "type": "OPEN_SCHEMA_PAGE",
              "payload": {
                "@type": "type.googleapis.com/widgets.OpenSchemaPagePayload",
                "additional_data": {
                  "@type": "type.googleapis.com/widgets.GetFeedbackPageRequest.AdditionalData",
                  "post_token": "Aa9yxyiS"
                },
                "is_modal": true,
                "rest_request_path": "/v8/post-quality/feedback-v2",
                "grpc_request_path": "/post_quality.PostQualityFeedback/GetFeedbackPage"
              }
            },
            "has_divider": true,
            "icon": {
              "image_url_dark": "https://s100.divarcdn.com/static/imgs/widget-icons/dark/icon_secondary/v1/report.png",
              "image_url_light": "https://s100.divarcdn.com/static/imgs/widget-icons/light/icon_secondary/v1/report.png",
              "icon_name": "REPORT",
              "icon_color": "ICON_SECONDARY"
            },
            "has_arrow": true,
            "last_notification_date": "0001-01-01T00:00:00Z"
          }
        }
      ]
    }
  ],
  "share": {
    "title": "ساخت و تعمیر سویچ و ریموت انواع خودرو",
    "web_url": "https://divar.ir/v/Aa9yxyiS"
  },
  "seo": {
    "title": "ساخت و تعمیر سویچ و ریموت انواع خودرو در مشهد",
    "description": "آگهی ساخت و تعمیر سویچ و ریموت انواع خودرو در دیوار مشهد",
    "android_package_name": "ir.divar",
    "android_app_url": "android-app://ir.divar/http/v/ساخت و تعمیر سویچ و ریموت انواع خودرو/Aa9yxyiS/",
    "web_info": {
      "title": "ساخت و تعمیر سویچ و ریموت انواع خودرو",
      "district_persian": "آزادشهر",
      "city_persian": "مشهد",
      "category_slug_persian": "قطعات یدکی و لوازم جانبی"
    },
    "unavailable_after": "2025-11-10T09:41:02.443384",
    "bread_crumb": [
      {
        "name": "قطعات یدکی و لوازم جانبی",
        "search_data": {
          "form_data": {
            "data": {
              "category": {
                "str": {
                  "value": "parts-accessories"
                }
              },
              "districts": {
                "repeated_string": {
                  "value": [
                    "431"
                  ]
                }
              }
            }
          }
        }
      },
      {
        "name": "وسایل نقلیه",
        "search_data": {
          "form_data": {
            "data": {
              "category": {
                "str": {
                  "value": "vehicles"
                }
              },
              "districts": {
                "repeated_string": {
                  "value": [
                    "431"
                  ]
                }
              }
            }
          }
        }
      },
      {
        "name": "آزادشهر",
        "search_data": {
          "form_data": {
            "data": {
              "districts": {
                "repeated_string": {
                  "value": [
                    "431"
                  ]
                }
              }
            }
          }
        }
      },
      {
        "name": "3",
        "search_data": {
          "form_data": {}
        }
      },
      {
        "name": "دیوار"
      }
    ],
    "post_seo_schema": {
      "url": "https://divar.ir/v/ساخت-و-تعمیر-سویچ-و-ریموت-انواع-خودرو/Aa9yxyiS",
      "description": "• ساخت سویچ و ریموت گمشده انواع خودروهای ایرانی و خارجی  \n• تعمیر و کددهی ریموت دزدگیر  \n• نصب انواع جی پی اس   \n• خدمات سریع و تخصصی در محل  \n• فروشگاه معتبر در نبش جلال آل احمد ۵۹  \nبرای مشاوره و قیمت، تماس بگیرید!",
      "image": "https://s100.divarcdn.com/static/photo/neda/post/_NsFyCivVhl-G2jKoaqVew/f80780a4-cb6f-4a5f-9228-20d9a7b71e89.jpg.jpg",
      "offers": {
        "@type": "Offer",
        "priceCurrency": "IRR",
        "price": "12000"
      },
      "name": "ساخت و تعمیر سویچ و ریموت انواع خودرو",
      "category": "parts-accessories",
      "@context": "https://schema.org",
      "web_info": {
        "category_slug_persian": "قطعات یدکی و لوازم جانبی",
        "title": "ساخت و تعمیر سویچ و ریموت انواع خودرو",
        "city_persian": "مشهد",
        "district_persian": "آزادشهر"
      },
      "@type": "Product"
    }
  },
  "contact": {
    "chat_enabled": true,
    "action_log": {
      "server_side_info": {
        "info": {
          "@type": "type.googleapis.com/action_log.ContactInfoInfo",
          "post_token": "Aa9yxyiS",
          "method_name": "GetContactWeb",
          "contact_uuid": "6b103eb7-c05a-414d-aecb-8c717cdf1358"
        },
        "item_type": {
          "type": "CONTACT_INFO"
        }
      },
      "enabled": true
    },
    "contact_uuid": "6b103eb7-c05a-414d-aecb-8c717cdf1358"
  },
  "webengage": {
    "status": "",
    "cat_1": "vehicles",
    "business_ref": "",
    "originality": "",
    "gender": "",
    "token": "Aa9yxyiS",
    "business_type": "personal",
    "district": "azadshahr",
    "cat_3": "",
    "category": "parts-accessories",
    "city": "mashhad",
    "source_view": "",
    "brand_model": "",
    "price": 12000,
    "credit": 0,
    "rent": 0,
    "cat_2": "parts-accessories",
    "image_count": 7
  },
  "analytics": {
    "cat1": "vehicles",
    "cat2": "parts-accessories",
    "city": "mashhad"
  },
  "city": {
    "city_id": "3",
    "name": "مشهد",
    "parent_id": "880",
    "second_slug": "mashhad"
  }
}